sysDB/__init__.py
sysDB/scrapedx64.pickle
sysDB/scrapedx86.pickle
sysDB/sysDB.py
sysDB/syscallLookup/scrapedx64.pickle
sysDB/syscallLookup/scrapedx86.pickle
sysDB/syscallLookup/scrape/syscallScrapex64.py
sysDB/syscallLookup/scrape/syscallScrapex86.py
sysDB-0.1.data/scripts/__init__.py
sysDB-0.1.data/scripts/sysDB.py
sysDB-0.1.dist-info/LICENSE
sysDB-0.1.dist-info/METADATA
sysDB-0.1.dist-info/WHEEL
sysDB-0.1.dist-info/top_level.txt
sysDB-0.1.dist-info/RECORD
