Metadata-Version: 2.1
Name: sysDB
Version: 0.1
Summary: A x86 and x64 syscall database
Home-page: https://github.com/marwenn02/syscallDB
Author: nnewram
Author-email: marwenn02@gmail.com
License: UNKNOWN
Platform: UNKNOWN
Classifier: Programming Language :: Python :: 3
Classifier: License :: OSI Approved :: MIT License
Classifier: Operating System :: OS Independent
